neets/__init__.py
neets/completions.py
neets/neets.py
neets/tts.py
neets/utils.py
neets-0.0.4.dist-info/LICENSE
neets-0.0.4.dist-info/METADATA
neets-0.0.4.dist-info/WHEEL
neets-0.0.4.dist-info/entry_points.txt
neets-0.0.4.dist-info/top_level.txt
neets-0.0.4.dist-info/RECORD
