Metadata-Version: 2.1
Name: neets
Version: 0.0.4
Summary: CLI to interact with the neets.ai API
Home-page: https://github.com/NotJoeMartinez/neets-api-cli
Author: NotJoeMartinez
Requires-Python: >=3.8
License-File: LICENSE
Requires-Dist: certifi ==2023.11.17
Requires-Dist: charset-normalizer ==3.3.2
Requires-Dist: click ==8.1.7
Requires-Dist: idna ==3.6
Requires-Dist: markdown-it-py ==3.0.0
Requires-Dist: mdurl ==0.1.2
Requires-Dist: Pygments ==2.17.2
Requires-Dist: requests ==2.31.0
Requires-Dist: rich ==13.7.0
Requires-Dist: urllib3 ==2.1.0
